{
  "description": "Reflection – general partnership development. Indicate how much you agree with each statement about how you show up in relationships, projects, and shared experiences.",
  "questions": [
    {
      "id": "R1",
      "archetype": "Catalyst",
      "question_text": "When things stall, I naturally bring playful energy and momentum back into the mix.",
      "type": "likert_scale",
      "weight": 2,
      "response_options": ["Strongly agree","Somewhat agree","Neutral","Somewhat disagree","Strongly disagree"]
    },
    {
      "id": "R2",
      "archetype": "Explorer",
      "question_text": "I feel most alive when we try new places, activities, or approaches together.",
      "type": "likert_scale",
      "weight": 2,
      "response_options": ["Strongly agree","Somewhat agree","Neutral","Somewhat disagree","Strongly disagree"]
    },
    {
      "id": "R3",
      "archetype": "Oracle",
      "question_text": "I regularly reflect on my own growth and how it affects the relationship.",
      "type": "likert_scale",
      "weight": 2,
      "response_options": ["Strongly agree","Somewhat agree","Neutral","Somewhat disagree","Strongly disagree"]
    },
    {
      "id": "R4",
      "archetype": "Keystone",
      "question_text": "I balance my appetite for novelty with a steady sense of care and reliability.",
      "type": "likert_scale",
      "weight": 2,
      "response_options": ["Strongly agree","Somewhat agree","Neutral","Somewhat disagree","Strongly disagree"]
    },
    {
      "id": "R5",
      "archetype": "Connoisseur",
      "question_text": "The aesthetic quality and attention to detail in shared experiences is deeply fulfilling to me.",
      "type": "likert_scale",
      "weight": 2,
      "response_options": ["Strongly agree","Somewhat agree","Neutral","Somewhat disagree","Strongly disagree"]
    },
    {
      "id": "R6",
      "archetype": "Keystone",
      "question_text": "I communicate and maintain my boundaries consistently, even during emotional moments.",
      "type": "likert_scale",
      "weight": 2,
      "response_options": ["Strongly agree","Somewhat agree","Neutral","Somewhat disagree","Strongly disagree"]
    },
    {
      "id": "R7",
      "archetype": "Vanguard",
      "question_text": "When stakes rise, I’m comfortable stepping into clear leadership to move us forward.",
      "type": "likert_scale",
      "weight": 2,
      "response_options": ["Strongly agree","Somewhat agree","Neutral","Somewhat disagree","Strongly disagree"]
    },
    {
      "id": "R8",
      "archetype": "Oracle",
      "question_text": "If communication breaks down, I help restore clarity and trust without escalating conflict.",
      "type": "likert_scale",
      "weight": 2,
      "response_options": ["Strongly agree","Somewhat agree","Neutral","Somewhat disagree","Strongly disagree"]
    },
    {
      "id": "R9",
      "archetype": "Explorer",
      "question_text": "Taking measured risks together often leads to learning and growth for me.",
      "type": "likert_scale",
      "weight": 2,
      "response_options": ["Strongly agree","Somewhat agree","Neutral","Somewhat disagree","Strongly disagree"]
    },
    {
      "id": "R10",
      "archetype": "Alchemist",
      "question_text": "Designing small rituals or intentional frames helps transform ordinary moments into something meaningful.",
      "type": "likert_scale",
      "weight": 2,
      "response_options": ["Strongly agree","Somewhat agree","Neutral","Somewhat disagree","Strongly disagree"]
    },
    {
      "id": "R11",
      "archetype": "Vanguard",
      "question_text": "I actively seek feedback and use it to sharpen how I guide or set direction.",
      "type": "likert_scale",
      "weight": 2,
      "response_options": ["Strongly agree","Somewhat agree","Neutral","Somewhat disagree","Strongly disagree"]
    },
    {
      "id": "R12",
      "archetype": "Catalyst",
      "question_text": "Playful challenges or mini-dares tend to re-connect me with partners and shared goals.",
      "type": "likert_scale",
      "weight": 2,
      "response_options": ["Strongly agree","Somewhat agree","Neutral","Somewhat disagree","Strongly disagree"]
    }
  ]
}
